<?xml version="1.0" encoding="UTF-8"?>
<monster name="Wild Warrior" nameDescription="a wild warrior" race="blood" experience="60" speed="190" manacost="420">
	<health now="135" max="135"/>
	<look type="131" head="38" body="38" legs="38" feet="38" addons="0" corpse="20534"/>
	<targetchange interval="2000" chance="0"/>
	<flags>
		<flag summonable="1"/>
		<flag attackable="1"/>
		<flag hostile="1"/>
		<flag illusionable="1"/>
		<flag convinceable="1"/>
		<flag pushable="1"/>
		<flag canpushitems="0"/>
		<flag canpushcreatures="0"/>
		<flag staticattack="90"/>
		<flag targetdistance="1"/>
		<flag runonhealth="10"/>
	</flags>
	<attacks>
		<attack name="melee" interval="2000" skill="60" attack="20"/>
	</attacks>
	<defenses armor="8" defense="10">
		<defense name="speed" interval="2000" chance="6" speedchange="240" duration="4000">
			<attribute key="areaEffect" value="redshimmer"/>
		</defense>
	</defenses>
	<elements>
		<element holyPercent="10"/>
		<element physicalPercent="-10"/>
		<element deathPercent="-5"/>
	</elements>
	<voices interval="2000" chance="5">
		<voice sentence="An enemy!"/>
		<voice sentence="Gimme your money!"/>
	</voices>
	<loot>
		<item id="2148" countmax="30" chance="49120"/><!-- gold coin -->
		<item id="2328" countmax="2" chance="9740"/><!-- egg -->
		<item id="2110" chance="520"/><!-- doll -->
		<item id="2398" chance="9800"/><!-- mace -->
		<item id="2465" chance="2500"/><!-- brass armor -->
		<item id="2509" chance="910"/><!-- steel shield -->
		<item id="2386" chance="30710"/><!-- axe -->
		<item id="2458" chance="5110"/><!-- chain helmet -->
		<item id="2511" chance="16890"/><!-- brass shield -->
		<item id="2459" chance="570"/><!-- iron helmet -->
	</loot>
</monster>
